[
    {
        "name": "Open Source",
        "sub-portfolios": [
            {
                "name": "shor10",
                "description": "Link shortener app with Meteor and React",
                "source": "https://github.com/bala92x/shor10",
                "url": "https://shor10.herokuapp.com"
            },
            {
                "name": "expensify",
                "description": "Expense manager application with React, Redux, and Firebase",
                "source": "https://github.com/bala92x/expensify",
                "demo": "https://bala-expensify.herokuapp.com"
            },
            {
                "name": "chat-app",
                "description": "Simple Node.js based chat app with socket.io integration",
                "source": "https://github.com/bala92x/chat-app",
                "url": "https://brit-tudosok-chat.herokuapp.com"
            },
            {
                "name": "score-keeper",
                "description": "Simple score keeper app with Meteor and React",
                "source": "https://github.com/bala92x/score-keeper",
                "url": "https://bala-score-keeper.herokuapp.com"
            },
            {
                "name": "indecision-app",
                "description": "Simple decision maker app with React",
                "source": "https://github.com/bala92x/indecision-app",
                "demo": "http://bala-indecision-app.herokuapp.com"
            },
            {
                "name": "task-manager",
                "description": "Node.js task manager API with JWT authorization",
                "source": "https://github.com/bala92x/task-manager",
                "url": "https://bala-task-manager.herokuapp.com"
            },
            {
                "more": "More open source projects: https://github.com/bala92x"
            }
        ]
    },
    {
        "name": "Projects I contributed to",
        "sub-portfolios": [
            {
                "name": "Agora Lakópark",
                "description": "Website of an 11 building residential park, with complex administration backend",
                "url": "https://agorapark.hu",
                "framework": "Laravel 5.3"
            },
            {
                "name": "Pannon Oktatási Központ",
                "description": "Website of an educational institution, with administration backend and the opportunity of signing up for courses",
                "url": "https://www.oktatasioldal.hu",
                "framework": "Laravel 5.4"
            },
            {
                "name": "Auto Finesse webshop",
                "description": "Webshop of car detailing products. Hundreds of products, several payment options and Facebook Shop synchronization",
                "url": "https://afshop.hu",
                "CMS": "WordPress"
            },
            {
                "name": "Micsoda esküvő",
                "description": "Portfolio site of a marriage celebrant",
                "url": "https://kulonlegesszertartas.hu",
                "CMS": "WordPress"
            },
            {
                "more": "More projects I contributed to: https://brandingpage.hu"
            }
        ]
    }
]